gitredate/__init__.py
gitredate/__main__.py
gitredate/chart.py
gitredate/main.py
gitredate/utils.py
gitredate-0.1.0.dist-info/METADATA
gitredate-0.1.0.dist-info/WHEEL
gitredate-0.1.0.dist-info/entry_points.txt
gitredate-0.1.0.dist-info/top_level.txt
gitredate-0.1.0.dist-info/RECORD
