Metadata-Version: 2.4
Name: gitredate
Version: 0.1.0
Summary: Rewrite date of Git commits
Requires-Python: >=3.13
Requires-Dist: bokeh>=3.7.3
Requires-Dist: businesstimedelta>=1.0.1
Requires-Dist: dateparser>=1.2.2
Requires-Dist: gitpython>=3.1.45
Requires-Dist: python-dateutil>=2.9.0.post0
Requires-Dist: pytz>=2025.2
Requires-Dist: typer>=0.16.0
Requires-Dist: tzlocal>=5.3.1
